corrigo/__init__.py
corrigo/auth.py
corrigo/cli.py
corrigo/client.py
corrigo/config.py
corrigo/events.py
corrigo/exceptions.py
corrigo/http.py
corrigo/output.py
corrigo/api/__init__.py
corrigo/api/base.py
corrigo/api/commands.py
corrigo/api/query.py
corrigo/api/resources/__init__.py
corrigo/api/resources/contacts.py
corrigo/api/resources/customers.py
corrigo/api/resources/employees.py
corrigo/api/resources/invoices.py
corrigo/api/resources/locations.py
corrigo/api/resources/work_orders.py
corrigo/api/resources/work_zones.py
corrigo/models/__init__.py
corrigo/models/base.py
corrigo/models/enums.py
corrigo-0.1.0.dist-info/METADATA
corrigo-0.1.0.dist-info/WHEEL
corrigo-0.1.0.dist-info/entry_points.txt
corrigo-0.1.0.dist-info/licenses/LICENSE
corrigo-0.1.0.dist-info/RECORD
