Metadata-Version: 2.4
Name: corrigo
Version: 0.1.0
Summary: Python SDK for the Corrigo Enterprise REST API
Project-URL: Homepage, https://github.com/ssbean/corrigo-python
Project-URL: Documentation, https://github.com/ssbean/corrigo-python#readme
Project-URL: Repository, https://github.com/ssbean/corrigo-python
Project-URL: Issues, https://github.com/ssbean/corrigo-python/issues
Author: Spencer Bean
License-Expression: MIT
License-File: LICENSE
Keywords: api,corrigo,facilities,sdk,work-orders
Classifier: Development Status :: 3 - Alpha
Classifier: Intended Audience :: Developers
Classifier: License :: OSI Approved :: MIT License
Classifier: Operating System :: OS Independent
Classifier: Programming Language :: Python :: 3
Classifier: Programming Language :: Python :: 3.9
Classifier: Programming Language :: Python :: 3.10
Classifier: Programming Language :: Python :: 3.11
Classifier: Programming Language :: Python :: 3.12
Classifier: Typing :: Typed
Requires-Python: >=3.9
Requires-Dist: httpx>=0.25.0
Requires-Dist: pydantic>=2.0.0
Requires-Dist: python-dateutil>=2.8.0
Requires-Dist: tenacity>=8.0.0
Provides-Extra: cli
Requires-Dist: pyyaml>=6.0.0; extra == 'cli'
Requires-Dist: rich>=13.0.0; extra == 'cli'
Requires-Dist: typer>=0.9.0; extra == 'cli'
Provides-Extra: dev
Requires-Dist: mypy>=1.0.0; extra == 'dev'
Requires-Dist: pre-commit>=3.0.0; extra == 'dev'
Requires-Dist: pytest-asyncio>=0.21.0; extra == 'dev'
Requires-Dist: pytest-cov>=4.0.0; extra == 'dev'
Requires-Dist: pytest>=7.0.0; extra == 'dev'
Requires-Dist: respx>=0.20.0; extra == 'dev'
Requires-Dist: ruff>=0.1.0; extra == 'dev'
Provides-Extra: docs
Requires-Dist: mkdocs-material>=9.0.0; extra == 'docs'
Requires-Dist: mkdocs>=1.5.0; extra == 'docs'
Requires-Dist: mkdocstrings[python]>=0.24.0; extra == 'docs'
